dnfile/__init__.py
dnfile/base.py
dnfile/codedindex.py
dnfile/enums.py
dnfile/errors.py
dnfile/mdtable.py
dnfile/py.typed
dnfile/resource.py
dnfile/stream.py
dnfile/utils.py
dnfile-0.15.1.dist-info/LICENSE
dnfile-0.15.1.dist-info/METADATA
dnfile-0.15.1.dist-info/WHEEL
dnfile-0.15.1.dist-info/top_level.txt
dnfile-0.15.1.dist-info/RECORD
