Metadata-Version: 2.1
Name: dnfile
Version: 0.15.1
Summary: Parse .NET executable files.
Author: MalwareFrank
License: MIT License
Project-URL: repository, https://github.com/malwarefrank/dnfile
Keywords: dnfile
Classifier: Development Status :: 4 - Beta
Classifier: Intended Audience :: Developers
Classifier: License :: OSI Approved :: MIT License
Classifier: Natural Language :: English
Classifier: Programming Language :: Python :: 3
Classifier: Programming Language :: Python :: 3.8
Classifier: Programming Language :: Python :: 3.9
Requires-Python: >=3.8
License-File: LICENSE
Requires-Dist: pefile>=2019.4.18
